lca_disclosures/__init__.py
lca_disclosures/flow_types.py
lca_disclosures/utils.py
lca_disclosures/antelope/__init__.py
lca_disclosures/antelope/foreground_observer.py
lca_disclosures/antelope/observer.py
lca_disclosures/antelope/traversal_observer.py
lca_disclosures/base/__init__.py
lca_disclosures/base/disclosure.py
lca_disclosures/base/from_file.py
lca_disclosures/lcopt/__init__.py
lca_disclosures/lcopt/disclosure.py
lca_disclosures-0.2.0rc2.dist-info/LICENSE
lca_disclosures-0.2.0rc2.dist-info/METADATA
lca_disclosures-0.2.0rc2.dist-info/WHEEL
lca_disclosures-0.2.0rc2.dist-info/top_level.txt
lca_disclosures-0.2.0rc2.dist-info/RECORD
