Metadata-Version: 2.1
Name: lca-disclosures
Version: 0.2.0rc2
Summary: Python based tools for working with LCA foreground model disclosures
Home-page: https://github.com/AntelopeLCA/lca_disclosures/
Author: Brandon Kuczenski
Author-email: bkuczenski@ucsb.edu
License: BSD 3-Clause
Keywords: LCA,Life Cycle Assessment,Foreground system,Background system,Foreground model
Platform: UNKNOWN
Classifier: Intended Audience :: End Users/Desktop
Classifier: Intended Audience :: Developers
Classifier: Intended Audience :: Science/Research
Classifier: License :: OSI Approved :: BSD License
Classifier: Operating System :: MacOS :: MacOS X
Classifier: Operating System :: Microsoft :: Windows
Classifier: Operating System :: POSIX
Classifier: Programming Language :: Python
Classifier: Programming Language :: Python :: 3
Classifier: Programming Language :: Python :: 3.4
Classifier: Programming Language :: Python :: 3.5
Classifier: Topic :: Scientific/Engineering :: Information Analysis
Classifier: Topic :: Scientific/Engineering :: Mathematics
Classifier: Topic :: Scientific/Engineering :: Visualization
Requires-Dist: scipy (>=1.5.2)
Requires-Dist: pandas (>=1.1.2)
Requires-Dist: openpyxl (>=3.0.5)
